odoo8_addon_product_tag-8.0.1.0.0.99.dev2-py3.8-nspkg.pth
odoo_addons/product_tag/README.rst
odoo_addons/product_tag/__init__.py
odoo_addons/product_tag/__openerp__.py
odoo_addons/product_tag/models/__init__.py
odoo_addons/product_tag/models/product.py
odoo_addons/product_tag/security/ir.model.access.csv
odoo_addons/product_tag/views/product_tag_view.xml
odoo_addons/product_tag/views/product_view.xml
odoo8_addon_product_tag-8.0.1.0.0.99.dev2.dist-info/METADATA
odoo8_addon_product_tag-8.0.1.0.0.99.dev2.dist-info/WHEEL
odoo8_addon_product_tag-8.0.1.0.0.99.dev2.dist-info/namespace_packages.txt
odoo8_addon_product_tag-8.0.1.0.0.99.dev2.dist-info/top_level.txt
odoo8_addon_product_tag-8.0.1.0.0.99.dev2.dist-info/RECORD
